odoo/addons/mrp_bom_tracking/README.rst
odoo/addons/mrp_bom_tracking/__init__.py
odoo/addons/mrp_bom_tracking/__manifest__.py
odoo/addons/mrp_bom_tracking/i18n/de.po
odoo/addons/mrp_bom_tracking/i18n/mrp_bom_tracking.pot
odoo/addons/mrp_bom_tracking/models/__init__.py
odoo/addons/mrp_bom_tracking/models/mrp_bom.py
odoo/addons/mrp_bom_tracking/readme/CONTRIBUTORS.rst
odoo/addons/mrp_bom_tracking/readme/DESCRIPTION.rst
odoo/addons/mrp_bom_tracking/static/description/icon.png
odoo/addons/mrp_bom_tracking/static/description/index.html
odoo/addons/mrp_bom_tracking/tests/__init__.py
odoo/addons/mrp_bom_tracking/tests/test_mrp_bom_tracking.py
odoo/addons/mrp_bom_tracking/views/bom_template.xml
odoo13_addon_mrp_bom_tracking-13.0.1.0.1.dist-info/METADATA
odoo13_addon_mrp_bom_tracking-13.0.1.0.1.dist-info/WHEEL
odoo13_addon_mrp_bom_tracking-13.0.1.0.1.dist-info/top_level.txt
odoo13_addon_mrp_bom_tracking-13.0.1.0.1.dist-info/RECORD
